Metadata-Version: 2.1
Name: krozark-functils
Version: 0.1.2
Summary: The aim of this project is to group some usefull python class
Home-page: https://github.com/Krozark/py-functils
Author: Maxime Barbier
Author-email: maxime.barbier1991+py-functils@gmail.com
License: BSD2
Keywords: funcutils
Requires-Dist: requests
Requires-Dist: types-requests
Requires-Dist: jinja2
Requires-Dist: file-magic (==0.4.*)
Provides-Extra: dev
Requires-Dist: black ; extra == 'dev'
Requires-Dist: coverage ; extra == 'dev'
Requires-Dist: docformatter ; extra == 'dev'
Requires-Dist: flake8 ; extra == 'dev'
Requires-Dist: isort ; extra == 'dev'
Requires-Dist: mypy ; extra == 'dev'
Requires-Dist: pre-commit ; extra == 'dev'
Requires-Dist: pylint ; extra == 'dev'
Requires-Dist: ipython ; extra == 'dev'
